{
		ingredientPattern:"LOL,IDC,LOL",
		ingredients: {
			"L": { type: "block", code: "game:supportbeam-oak", quantity:16},
			"O": { type: "item", code: "game:metalnailsandstrips-*", "name": "metal","allowedVariants": ["iron"], quantity: 6},
			"I": { type: "item", code: "game:hammer-*", isTool: true, toolDurabilityCost: 30 },
			"D": { type: "item", code: "game:rope", quantity:5},
			"C": { type: "item", code: "game:saw-*", isTool: true, toolDurabilityCost: 30 }
		},
	width: 3,
	height: 3,
	output: { type: "item", code: "mechgantryitem-mechgantryfake"  }
}